responser.py
responser-1.0.0.data/scripts/setup_script
responser-1.0.0.dist-info/LICENSE
responser-1.0.0.dist-info/METADATA
responser-1.0.0.dist-info/WHEEL
responser-1.0.0.dist-info/top_level.txt
responser-1.0.0.dist-info/RECORD
