Metadata-Version: 2.1
Name: responser
Version: 1.0.0
Summary: Responser is a python package to convert normal strings, objects and other data to REST API response convention and in JSON format.
Home-page: https://github.com/BharathKumarRavichandran/responser/
Author: Bharath Kumar Ravichandran
Author-email: bharathkumarravichandran@gmail.com
License: MIT
Keywords: responser json api decorator
Platform: UNKNOWN
Classifier: License :: OSI Approved :: MIT License
Classifier: Operating System :: OS Independent
Classifier: Programming Language :: Python :: 2
Classifier: Programming Language :: Python :: 2.6
Classifier: Programming Language :: Python :: 2.7
Classifier: Programming Language :: Python :: 3
Classifier: Programming Language :: Python :: 3.3
Classifier: Programming Language :: Python :: 3.6
